baseXtoY/__init__.py
baseXtoY/__main__.py
baseXtoY/_main/__init__.py
baseXtoY/_main/number.py
baseXtoY-1.2.post1.dist-info/LICENSE
baseXtoY-1.2.post1.dist-info/METADATA
baseXtoY-1.2.post1.dist-info/WHEEL
baseXtoY-1.2.post1.dist-info/top_level.txt
baseXtoY-1.2.post1.dist-info/RECORD
