Metadata-Version: 2.1
Name: baseXtoY
Version: 1.2.post1
Summary: A simple base converter in python3.
Home-page: https://github.com/toto112358/base-converter
Author: L. Pham-Trong
Author-email: spam@lucasanss.xyz
License: UNKNOWN
Platform: UNKNOWN
Classifier: Programming Language :: Python :: 3
Classifier: License :: OSI Approved :: BSD License
Classifier: Operating System :: OS Independent
Requires-Python: >=3.0
